[
  {
    "name": "Trefl",
    "count": 559
  },
  {
    "name": "Astra",
    "count": 529
  },
  {
    "name": "Interdruk",
    "count": 368
  },
  {
    "name": "bez marki",
    "count": 325
  },
  {
    "name": "Madej",
    "count": 299
  },
  {
    "name": "Koh-I-Noor",
    "count": 281
  },
  {
    "name": "Galeria Papieru",
    "count": 267
  },
  {
    "name": "GDD",
    "count": 246
  },
  {
    "name": "HAMELIN POLSKA SP. Z O.O.",
    "count": 237
  },
  {
    "name": "Vau-Pe",
    "count": 231
  },
  {
    "name": "Kidea",
    "count": 223
  },
  {
    "name": "Oxford",
    "count": 222
  },
  {
    "name": "Happy Color",
    "count": 207
  },
  {
    "name": "ARGO",
    "count": 205
  },
  {
    "name": "POL-MAK SP. Z O.O.",
    "count": 191
  },
  {
    "name": "Lisciani",
    "count": 161
  },
  {
    "name": "Askato",
    "count": 161
  },
  {
    "name": "Simba",
    "count": 160
  },
  {
    "name": "Stabilo",
    "count": 160
  },
  {
    "name": "Tetis",
    "count": 145
  },
  {
    "name": "Dalprint",
    "count": 137
  },
  {
    "name": "Parker",
    "count": 134
  },
  {
    "name": "Starpak",
    "count": 134
  },
  {
    "name": "TOP-2000",
    "count": 132
  },
  {
    "name": "KOH-I-NOOR HARDTMUTH POLSKA SP.ZO.O.",
    "count": 124
  },
  {
    "name": "Midex",
    "count": 116
  },
  {
    "name": "MICHALCZYK I PROKOP SPÓŁKA Z O.O.",
    "count": 116
  },
  {
    "name": "Titanum",
    "count": 110
  },
  {
    "name": "Clementoni",
    "count": 109
  },
  {
    "name": "Grand",
    "count": 105
  },
  {
    "name": "ASTRA SPÓŁKA AKCYJNA",
    "count": 97
  },
  {
    "name": "TREFL SPÓŁKA AKCYJNA",
    "count": 92
  },
  {
    "name": "BIC",
    "count": 86
  },
  {
    "name": "Bambino",
    "count": 85
  },
  {
    "name": "Dromader",
    "count": 85
  },
  {
    "name": "Milan",
    "count": 84
  },
  {
    "name": "Cubic Fun",
    "count": 80
  },
  {
    "name": "St. Majewski",
    "count": 79
  },
  {
    "name": "Mega Creative",
    "count": 79
  },
  {
    "name": "Beniamin",
    "count": 78
  },
  {
    "name": "Michalczyk i Prokop",
    "count": 77
  },
  {
    "name": "Donau",
    "count": 76
  },
  {
    "name": "Euro-Trade",
    "count": 75
  },
  {
    "name": "Dante",
    "count": 72
  },
  {
    "name": "KW TRADE SP Z O.O.",
    "count": 67
  },
  {
    "name": "BIC POLSKA SP. Z O.O",
    "count": 63
  },
  {
    "name": "WPC",
    "count": 63
  },
  {
    "name": "Cartamundi",
    "count": 62
  },
  {
    "name": "Bantex",
    "count": 61
  },
  {
    "name": "ALIGA - KATARZYNA I PAWEŁ GAŁĄZKA SPÓŁKA JAWNA",
    "count": 61
  },
  {
    "name": "Rystor",
    "count": 60
  },
  {
    "name": "Stnux",
    "count": 60
  },
  {
    "name": "Zielona Sowa",
    "count": 59
  },
  {
    "name": "KOSTAS GROUP SP.Z O.O.",
    "count": 58
  },
  {
    "name": "BIURFOL SPÓŁKA Z OGRANICZONĄ ODPOWIEDZIALNOŚCIĄ",
    "count": 57
  },
  {
    "name": "Pentel",
    "count": 56
  },
  {
    "name": "TADEO TRADING SP. Z O.O.",
    "count": 56
  },
  {
    "name": "Herlitz",
    "count": 52
  },
  {
    "name": "ALIGA",
    "count": 52
  },
  {
    "name": "Adamigo",
    "count": 51
  },
  {
    "name": "Aliga",
    "count": 50
  },
  {
    "name": "Office Products",
    "count": 47
  },
  {
    "name": "Argo",
    "count": 46
  },
  {
    "name": "LEGO",
    "count": 45
  },
  {
    "name": "Bburago",
    "count": 45
  },
  {
    "name": "Bestway",
    "count": 44
  },
  {
    "name": "Party Deco",
    "count": 44
  },
  {
    "name": "WYDAWNICTWO NIKO SP. Z O.O.",
    "count": 43
  },
  {
    "name": "NEWELL POLAND SERVICES SP. Z O.O.",
    "count": 43
  },
  {
    "name": "Keyroad",
    "count": 43
  },
  {
    "name": "PILOT",
    "count": 41
  },
  {
    "name": "Staedtler",
    "count": 41
  },
  {
    "name": "VAUPE SP. Z O.O.",
    "count": 41
  },
  {
    "name": "DpCraft",
    "count": 40
  },
  {
    "name": "M&G",
    "count": 38
  },
  {
    "name": "Faber-Castell",
    "count": 37
  },
  {
    "name": "TIERRA GROUP Sp. z o.o. Sp. K",
    "count": 37
  },
  {
    "name": "Hipo",
    "count": 36
  },
  {
    "name": "Cartotecnica Rossi",
    "count": 36
  },
  {
    "name": "GRUPA WYDAWNICZA MEDIA RODZINA SPÓŁKA Z O.O",
    "count": 36
  },
  {
    "name": "MP POLAND SPÓŁKA Z OGRANICZONĄ ODPOWIEDZIALNOŚCIĄ",
    "count": 34
  },
  {
    "name": "Pastello",
    "count": 34
  },
  {
    "name": "Welly",
    "count": 34
  },
  {
    "name": "Eagle",
    "count": 33
  },
  {
    "name": "Kukuryku",
    "count": 32
  },
  {
    "name": "ROZETTE SPÓŁKA Z OGRANICZONĄ ODPOWIEDZIALNOŚCIĄ",
    "count": 32
  },
  {
    "name": "Maped",
    "count": 30
  },
  {
    "name": "Abino",
    "count": 30
  },
  {
    "name": "nieznany producent",
    "count": 28
  },
  {
    "name": "Waterman",
    "count": 27
  },
  {
    "name": "EUROPAPIER POLSKA SP.Z O.O.",
    "count": 27
  },
  {
    "name": "Nadwyraz",
    "count": 27
  },
  {
    "name": "Paper Mate",
    "count": 26
  },
  {
    "name": "Derform",
    "count": 26
  },
  {
    "name": "GoDan",
    "count": 26
  },
  {
    "name": "Biurfol",
    "count": 25
  },
  {
    "name": "CZAPSKA SPÓŁKA KOMANDYTOWA",
    "count": 25
  },
  {
    "name": "Unipap",
    "count": 24
  },
  {
    "name": "Granna",
    "count": 24
  },
  {
    "name": "BamBam",
    "count": 24
  },
  {
    "name": "Kamet",
    "count": 23
  },
  {
    "name": "AVERY ZWECKFORM GMBH",
    "count": 23
  },
  {
    "name": "Dickie Toys",
    "count": 23
  },
  {
    "name": "Gimboo",
    "count": 23
  },
  {
    "name": "WYDAWNICTWO \"NIKO\" S.C.KRZEMIONKA,SOBIERALSKI",
    "count": 22
  },
  {
    "name": "Adar",
    "count": 21
  },
  {
    "name": "STABILO POLSKA",
    "count": 20
  },
  {
    "name": "HERLITZ PRZEŹMIEROWO",
    "count": 20
  },
  {
    "name": "PBS CONNECT POLSKA SP. Z O.O.",
    "count": 20
  },
  {
    "name": "Canson",
    "count": 19
  },
  {
    "name": "Paso",
    "count": 18
  },
  {
    "name": "Deef",
    "count": 18
  },
  {
    "name": "Sun-Day",
    "count": 18
  },
  {
    "name": "Lego",
    "count": 18
  },
  {
    "name": "Sharpie",
    "count": 17
  },
  {
    "name": "Toma",
    "count": 17
  },
  {
    "name": "Back Up",
    "count": 17
  },
  {
    "name": "Titanum Zenon Waniak Spółka Komandytowa",
    "count": 17
  },
  {
    "name": "St. Majewski Spółka z.o.o",
    "count": 17
  },
  {
    "name": "Penmate",
    "count": 16
  },
  {
    "name": "Mondi",
    "count": 16
  },
  {
    "name": "Bigo",
    "count": 16
  },
  {
    "name": "MILAN POLSKA SP.Z.O.O.",
    "count": 16
  },
  {
    "name": "Tres",
    "count": 16
  },
  {
    "name": "FILA POLSKA SPÓŁKA",
    "count": 16
  },
  {
    "name": "Fiorello",
    "count": 16
  },
  {
    "name": "Alleblox",
    "count": 16
  },
  {
    "name": "Bam Bam",
    "count": 16
  },
  {
    "name": "Jada Toys",
    "count": 16
  },
  {
    "name": "Strigo",
    "count": 15
  },
  {
    "name": "Hamelin",
    "count": 15
  },
  {
    "name": "Q-connect",
    "count": 15
  },
  {
    "name": "KW Trade",
    "count": 14
  },
  {
    "name": "Zenith",
    "count": 14
  },
  {
    "name": "ALFA spółka cywilna Bogusław Pilawa, Robert Szydło",
    "count": 14
  },
  {
    "name": "ST. MAJEWSKI SP. Z O. O.",
    "count": 13
  },
  {
    "name": "Schleich",
    "count": 13
  },
  {
    "name": "ASKATO SPÓŁKA Z O.O. SP. K.",
    "count": 13
  },
  {
    "name": "Rozette",
    "count": 13
  },
  {
    "name": "Antra",
    "count": 13
  },
  {
    "name": "Kum",
    "count": 12
  },
  {
    "name": "Rotring",
    "count": 12
  },
  {
    "name": "XQ",
    "count": 12
  },
  {
    "name": "Mattel",
    "count": 12
  },
  {
    "name": "Monami",
    "count": 12
  },
  {
    "name": "RYSTOR SPÓŁKA Z OGRANICZONĄ ODPOWIEDZIALNOŚCIĄ",
    "count": 12
  },
  {
    "name": "MP",
    "count": 12
  },
  {
    "name": "Fisher-Price",
    "count": 11
  },
  {
    "name": "Basic",
    "count": 11
  },
  {
    "name": "TULLO KATARZYNA ABRAMCZUK",
    "count": 11
  },
  {
    "name": "CzuCzu",
    "count": 11
  },
  {
    "name": "CDNORD",
    "count": 10
  },
  {
    "name": "Quercetti",
    "count": 10
  },
  {
    "name": "DELTA-GRAPHIX",
    "count": 10
  },
  {
    "name": "Malimas",
    "count": 10
  },
  {
    "name": "F.H.U. JU-PITER JACEK ŁUKASIAK",
    "count": 10
  },
  {
    "name": "Ge.Ma.R.",
    "count": 10
  },
  {
    "name": "GODAN S.A.",
    "count": 10
  },
  {
    "name": "DIPLO",
    "count": 10
  },
  {
    "name": "UNI",
    "count": 9
  },
  {
    "name": "TRODAT SP.Z O.O.",
    "count": 9
  },
  {
    "name": "TOMA SPÓŁKA Z OGRANICZONĄ ODPOWIEDZIALNOŚCIĄ",
    "count": 9
  },
  {
    "name": "Jupiter",
    "count": 9
  },
  {
    "name": "LESZKO",
    "count": 9
  },
  {
    "name": "Procos",
    "count": 9
  },
  {
    "name": "MC My Bubble",
    "count": 8
  },
  {
    "name": "Munhwa",
    "count": 8
  },
  {
    "name": "Clinex",
    "count": 8
  },
  {
    "name": "inna",
    "count": 8
  },
  {
    "name": "Trifox",
    "count": 8
  },
  {
    "name": "Hasbro",
    "count": 7
  },
  {
    "name": "Artyk",
    "count": 7
  },
  {
    "name": "Elba",
    "count": 7
  },
  {
    "name": "Spin Master",
    "count": 7
  },
  {
    "name": "Koh-i-noor",
    "count": 7
  },
  {
    "name": "POLIGRAF is",
    "count": 7
  },
  {
    "name": "Centropen",
    "count": 7
  },
  {
    "name": "Panta Plast",
    "count": 7
  },
  {
    "name": "Berlingo",
    "count": 7
  },
  {
    "name": "My Bubble",
    "count": 7
  },
  {
    "name": "TM Toys",
    "count": 7
  },
  {
    "name": "DERFORM SP. Z O.O.",
    "count": 7
  },
  {
    "name": "Carioca",
    "count": 7
  },
  {
    "name": "STNUX CHILIŃSKI I WSPÓLNICY SPÓŁKA JAWNA",
    "count": 7
  },
  {
    "name": "Tullo",
    "count": 7
  },
  {
    "name": "Smoby",
    "count": 7
  },
  {
    "name": "Barbie",
    "count": 7
  },
  {
    "name": "Bicycle",
    "count": 7
  },
  {
    "name": "Fru blu",
    "count": 7
  },
  {
    "name": "Flamingo Line",
    "count": 7
  },
  {
    "name": "Cricco",
    "count": 6
  },
  {
    "name": "LISCIANI GIOCHI",
    "count": 6
  },
  {
    "name": "IQ",
    "count": 6
  },
  {
    "name": "Mungyo",
    "count": 6
  },
  {
    "name": "A&G KOPERTY",
    "count": 6
  },
  {
    "name": "Z-Design",
    "count": 6
  },
  {
    "name": "DONAU TECH",
    "count": 6
  },
  {
    "name": "Avery",
    "count": 6
  },
  {
    "name": "John",
    "count": 6
  },
  {
    "name": "ToysInn",
    "count": 6
  },
  {
    "name": "Axel",
    "count": 6
  },
  {
    "name": "Newell",
    "count": 6
  },
  {
    "name": "TRIFOX SPÓŁKA Z OGRANICZONĄ ODPOWIEDZIALNOŚCIĄ",
    "count": 6
  },
  {
    "name": "ARTYK SP. Z O.O.",
    "count": 6
  },
  {
    "name": "Nice Group",
    "count": 6
  },
  {
    "name": "Inny producent",
    "count": 6
  },
  {
    "name": "Marek",
    "count": 6
  },
  {
    "name": "DARIUSZ ADAMIEC \"ADAR\" AGENCJA HANDLOWO-USŁUGOWA",
    "count": 6
  },
  {
    "name": "KWADRATURA KOŁA EWA FRĄCKIEWICZ",
    "count": 6
  },
  {
    "name": "Steffi",
    "count": 5
  },
  {
    "name": "Emerson",
    "count": 5
  },
  {
    "name": "Y-Plus",
    "count": 5
  },
  {
    "name": "Kamaben",
    "count": 5
  },
  {
    "name": "Toys",
    "count": 5
  },
  {
    "name": "Wallner",
    "count": 5
  },
  {
    "name": "Dong-A",
    "count": 5
  },
  {
    "name": "Oval",
    "count": 5
  },
  {
    "name": "CDC PL SPÓŁKA Z OGRANICZONĄ ODPOWIEDZIALNOŚCIĄ",
    "count": 5
  },
  {
    "name": "Pozostałe",
    "count": 5
  },
  {
    "name": "Memobe",
    "count": 5
  },
  {
    "name": "Tuban",
    "count": 5
  },
  {
    "name": "Majorette",
    "count": 5
  },
  {
    "name": "Niko",
    "count": 5
  },
  {
    "name": "Creatinio",
    "count": 5
  },
  {
    "name": "inny",
    "count": 5
  },
  {
    "name": "MARMAR",
    "count": 5
  },
  {
    "name": "Eugeniusz Kamiński \"KAMET\"",
    "count": 5
  },
  {
    "name": "Brother",
    "count": 5
  },
  {
    "name": "Dymo",
    "count": 5
  },
  {
    "name": "Flamingo",
    "count": 5
  },
  {
    "name": "FIRMA PRODUKCYJNO HANDLOWA ZACHEM Tadeusz GŁOWALA",
    "count": 5
  },
  {
    "name": "POL",
    "count": 4
  },
  {
    "name": "Amos",
    "count": 4
  },
  {
    "name": "MAR-BOR",
    "count": 4
  },
  {
    "name": "Poligraf",
    "count": 4
  },
  {
    "name": "CX DYSTRYBUCJA SP. Z O.O.",
    "count": 4
  },
  {
    "name": "Energizer",
    "count": 4
  },
  {
    "name": "Disney",
    "count": 4
  },
  {
    "name": "Tymos",
    "count": 4
  },
  {
    "name": "Drescher",
    "count": 4
  },
  {
    "name": "Koma-Plast",
    "count": 4
  },
  {
    "name": "Schneider",
    "count": 4
  },
  {
    "name": "F.H.U.  JU-PITER ALICJA ŁUKASIAK",
    "count": 4
  },
  {
    "name": "DAFFI SPÓŁKA Z OGRANICZONĄ ODPOWIEDZIALNOŚCIĄ",
    "count": 4
  },
  {
    "name": "KRIS-TEAM",
    "count": 4
  },
  {
    "name": "CUB",
    "count": 4
  },
  {
    "name": "AstraBag",
    "count": 4
  },
  {
    "name": "Brewis",
    "count": 4
  },
  {
    "name": "NERF",
    "count": 4
  },
  {
    "name": "ART AND PLAY",
    "count": 4
  },
  {
    "name": "Jan Niezbędny",
    "count": 4
  },
  {
    "name": "Panini",
    "count": 4
  },
  {
    "name": "Anna Zaradna",
    "count": 3
  },
  {
    "name": "Trodat",
    "count": 3
  },
  {
    "name": "PIONIER",
    "count": 3
  },
  {
    "name": "Vaupe",
    "count": 3
  },
  {
    "name": "Hero",
    "count": 3
  },
  {
    "name": "Tadeo Trading",
    "count": 3
  },
  {
    "name": "Bi-Office",
    "count": 3
  },
  {
    "name": "Noris",
    "count": 3
  },
  {
    "name": "Piatnik",
    "count": 3
  },
  {
    "name": "Enchantimals",
    "count": 3
  },
  {
    "name": "Avery-Zweckform",
    "count": 3
  },
  {
    "name": "PANTA-PLAST SP. Z O.O.",
    "count": 3
  },
  {
    "name": "CARTAMUNDI CARDS POLAND SP. z O.O.",
    "count": 3
  },
  {
    "name": "TRENDHAUS HANDELSGESELLSCHAFT MBH",
    "count": 3
  },
  {
    "name": "L.O.L. Surprise",
    "count": 3
  },
  {
    "name": "Cresco",
    "count": 3
  },
  {
    "name": "Portal Games",
    "count": 3
  },
  {
    "name": "DERFORM SP. J.       NIE PISAĆ",
    "count": 3
  },
  {
    "name": "DROMADER",
    "count": 3
  },
  {
    "name": "Mondo",
    "count": 3
  },
  {
    "name": "MALIMAS",
    "count": 3
  },
  {
    "name": "Jada",
    "count": 3
  },
  {
    "name": "Stella",
    "count": 3
  },
  {
    "name": "Goo Jit Zu",
    "count": 3
  },
  {
    "name": "National Geographic",
    "count": 3
  },
  {
    "name": "Forpus",
    "count": 3
  },
  {
    "name": "Aurora",
    "count": 3
  },
  {
    "name": "Asus",
    "count": 3
  },
  {
    "name": "ŚWIAT SPINEK",
    "count": 3
  },
  {
    "name": "Deli",
    "count": 3
  },
  {
    "name": "Office",
    "count": 3
  },
  {
    "name": "MK Trade",
    "count": 3
  },
  {
    "name": "POSCA",
    "count": 3
  },
  {
    "name": "inna (Inny)",
    "count": 3
  },
  {
    "name": "Go Party",
    "count": 3
  },
  {
    "name": "Grafix",
    "count": 3
  },
  {
    "name": "Kanex",
    "count": 3
  },
  {
    "name": "St.Right",
    "count": 3
  },
  {
    "name": "KIEL-TECH  SP.Z.O.O",
    "count": 3
  },
  {
    "name": "Konica minolta",
    "count": 3
  },
  {
    "name": "Natalia",
    "count": 2
  },
  {
    "name": "Heykka",
    "count": 2
  },
  {
    "name": "ARTYK ŁÓDŹ",
    "count": 2
  },
  {
    "name": "Esperanza",
    "count": 2
  },
  {
    "name": "VelvetCARE",
    "count": 2
  },
  {
    "name": "Artea",
    "count": 2
  },
  {
    "name": "Faber-castell",
    "count": 2
  },
  {
    "name": "Lancer",
    "count": 2
  },
  {
    "name": "Maestro",
    "count": 2
  },
  {
    "name": "AG",
    "count": 2
  },
  {
    "name": "Bic Kids",
    "count": 2
  },
  {
    "name": "MGA",
    "count": 2
  },
  {
    "name": "Tierra",
    "count": 2
  },
  {
    "name": "Elmer's",
    "count": 2
  },
  {
    "name": "4F",
    "count": 2
  },
  {
    "name": "Hot Wheels",
    "count": 2
  },
  {
    "name": "3Z",
    "count": 2
  },
  {
    "name": "Ico",
    "count": 2
  },
  {
    "name": "Drobiazgarnia",
    "count": 2
  },
  {
    "name": "Lacerta",
    "count": 2
  },
  {
    "name": "Toor",
    "count": 2
  },
  {
    "name": "Eichhorn",
    "count": 2
  },
  {
    "name": "METEOR CEE POLAND S.A",
    "count": 2
  },
  {
    "name": "NET S.C.",
    "count": 2
  },
  {
    "name": "Pelikan",
    "count": 2
  },
  {
    "name": "Inna|Evos",
    "count": 2
  },
  {
    "name": "Fun&Joy",
    "count": 2
  },
  {
    "name": "Michalczyk",
    "count": 2
  },
  {
    "name": "Rexus",
    "count": 2
  },
  {
    "name": "Play-Doh",
    "count": 2
  },
  {
    "name": "1DEA.me",
    "count": 2
  },
  {
    "name": "astra papiernicze",
    "count": 2
  },
  {
    "name": "Wader",
    "count": 2
  },
  {
    "name": "Rebel",
    "count": 2
  },
  {
    "name": "Memoboards",
    "count": 2
  },
  {
    "name": "inny|Top 2000",
    "count": 2
  },
  {
    "name": "3M",
    "count": 2
  },
  {
    "name": "Max Sport",
    "count": 2
  },
  {
    "name": "MG Home",
    "count": 2
  },
  {
    "name": "Pilsan",
    "count": 2
  },
  {
    "name": "MSpa",
    "count": 2
  },
  {
    "name": "GDD Grupa Dystrybucyjna Daccar",
    "count": 2
  },
  {
    "name": "MAREK SP. Z O.O.",
    "count": 2
  },
  {
    "name": "Majewski",
    "count": 2
  },
  {
    "name": "HASBRO POLAND SP. Z O.O.",
    "count": 2
  },
  {
    "name": "ASTRA Jacek T. Pazik",
    "count": 2
  },
  {
    "name": "HDPE",
    "count": 2
  },
  {
    "name": "MAT GROUP SPÓŁKA CYWILNA JACEK POŻARLIK I DOMINI",
    "count": 2
  },
  {
    "name": "TOTAL OFFICE TRADING",
    "count": 2
  },
  {
    "name": "BIGO",
    "count": 2
  },
  {
    "name": "AMEX STATIONERY SP. Z O.O.",
    "count": 2
  },
  {
    "name": "SPINMASTER",
    "count": 2
  },
  {
    "name": "Art And Play",
    "count": 2
  },
  {
    "name": "Simba Toys",
    "count": 2
  },
  {
    "name": "360",
    "count": 1
  },
  {
    "name": "inna|MALIMAS",
    "count": 1
  },
  {
    "name": "grand",
    "count": 1
  },
  {
    "name": "Doris",
    "count": 1
  },
  {
    "name": "Epee",
    "count": 1
  },
  {
    "name": "TETIS",
    "count": 1
  },
  {
    "name": "Van Manen",
    "count": 1
  },
  {
    "name": "Format",
    "count": 1
  },
  {
    "name": "Mikro Trading",
    "count": 1
  },
  {
    "name": "Craft",
    "count": 1
  },
  {
    "name": "Yn-Teen",
    "count": 1
  },
  {
    "name": "HC",
    "count": 1
  },
  {
    "name": "AS",
    "count": 1
  },
  {
    "name": "TM-TOYS SP. ZO.O.",
    "count": 1
  },
  {
    "name": "Kraft",
    "count": 1
  },
  {
    "name": "Świat Spinek",
    "count": 1
  },
  {
    "name": "Visual System",
    "count": 1
  },
  {
    "name": "Omeko",
    "count": 1
  },
  {
    "name": "DISTRI SP.Z O.O.",
    "count": 1
  },
  {
    "name": "iDesign",
    "count": 1
  },
  {
    "name": "Meto",
    "count": 1
  },
  {
    "name": "Merlando",
    "count": 1
  },
  {
    "name": "Incood",
    "count": 1
  },
  {
    "name": "BRANDED. ŚLIWIŃSKI SPÓŁKA KOMANDYTOWA",
    "count": 1
  },
  {
    "name": "AMEET POLSKA",
    "count": 1
  },
  {
    "name": "NC Koperty",
    "count": 1
  },
  {
    "name": "Iwako",
    "count": 1
  },
  {
    "name": "Silver",
    "count": 1
  },
  {
    "name": "IQ Color",
    "count": 1
  },
  {
    "name": "kukartka",
    "count": 1
  },
  {
    "name": "Omega",
    "count": 1
  },
  {
    "name": "Escuela",
    "count": 1
  },
  {
    "name": "Centrum",
    "count": 1
  },
  {
    "name": "Mona",
    "count": 1
  },
  {
    "name": "Verte",
    "count": 1
  },
  {
    "name": "Alexander",
    "count": 1
  },
  {
    "name": "Polesie",
    "count": 1
  },
  {
    "name": "Sferazabawek",
    "count": 1
  },
  {
    "name": "INTERPEN SP. Z O.O.",
    "count": 1
  },
  {
    "name": "Marie's",
    "count": 1
  },
  {
    "name": "Dodo",
    "count": 1
  },
  {
    "name": "Craft with Fun",
    "count": 1
  },
  {
    "name": "PASSION CARDS",
    "count": 1
  },
  {
    "name": "Lamps",
    "count": 1
  },
  {
    "name": "Oficio",
    "count": 1
  },
  {
    "name": "Daler Rowney",
    "count": 1
  },
  {
    "name": "Creativ",
    "count": 1
  },
  {
    "name": "IPICASSO SPÓŁKA Z OGRANICZONĄ ODPOWIEDZIALNOŚCIĄ",
    "count": 1
  },
  {
    "name": "V Trade",
    "count": 1
  },
  {
    "name": "ET",
    "count": 1
  },
  {
    "name": "Marmis",
    "count": 1
  },
  {
    "name": "Akuku",
    "count": 1
  },
  {
    "name": "EDGARD",
    "count": 1
  },
  {
    "name": "ootb",
    "count": 1
  },
  {
    "name": "Sadpex  Daniel, Przemysław Ślipko Spółka Jawna",
    "count": 1
  },
  {
    "name": "Avery zweckform",
    "count": 1
  },
  {
    "name": "Kolori",
    "count": 1
  },
  {
    "name": "Bard",
    "count": 1
  },
  {
    "name": "Pukka Pad",
    "count": 1
  },
  {
    "name": "Winsor & Newton",
    "count": 1
  },
  {
    "name": "Titanium",
    "count": 1
  },
  {
    "name": "KW",
    "count": 1
  },
  {
    "name": "MP Colours",
    "count": 1
  },
  {
    "name": "Shkolyaryk",
    "count": 1
  },
  {
    "name": "Uni",
    "count": 1
  },
  {
    "name": "Pollux",
    "count": 1
  },
  {
    "name": "DERFORM SP. J.",
    "count": 1
  },
  {
    "name": "Jokomisiada",
    "count": 1
  },
  {
    "name": "DeltaGraphix",
    "count": 1
  },
  {
    "name": "Steadtler",
    "count": 1
  },
  {
    "name": "inna|DIPLO",
    "count": 1
  },
  {
    "name": "ECOIFFIER",
    "count": 1
  },
  {
    "name": "inny|Ideal Quality",
    "count": 1
  },
  {
    "name": "Scooter",
    "count": 1
  },
  {
    "name": "CurePink",
    "count": 1
  },
  {
    "name": "ThinkFun",
    "count": 1
  },
  {
    "name": "Amex",
    "count": 1
  },
  {
    "name": "Colorino",
    "count": 1
  },
  {
    "name": "Tesa",
    "count": 1
  },
  {
    "name": "Creativo",
    "count": 1
  },
  {
    "name": "Pixie Crew",
    "count": 1
  },
  {
    "name": "U Wiktora",
    "count": 1
  },
  {
    "name": "Abro",
    "count": 1
  },
  {
    "name": "Creativ Company",
    "count": 1
  },
  {
    "name": "Post-it",
    "count": 1
  },
  {
    "name": "DAS",
    "count": 1
  },
  {
    "name": "MiPro",
    "count": 1
  },
  {
    "name": "M&C",
    "count": 1
  },
  {
    "name": "Plast",
    "count": 1
  },
  {
    "name": "Muse",
    "count": 1
  },
  {
    "name": "Prism",
    "count": 1
  },
  {
    "name": "VTech",
    "count": 1
  },
  {
    "name": "M&Z",
    "count": 1
  },
  {
    "name": "NORIMPEX",
    "count": 1
  },
  {
    "name": "LEAN Toys",
    "count": 1
  },
  {
    "name": "Lula Baby",
    "count": 1
  },
  {
    "name": "A-R",
    "count": 1
  },
  {
    "name": "Begris",
    "count": 1
  },
  {
    "name": "Multi",
    "count": 1
  },
  {
    "name": "OSUFI",
    "count": 1
  },
  {
    "name": "Maxell",
    "count": 1
  },
  {
    "name": "Gacek",
    "count": 1
  },
  {
    "name": "Protos",
    "count": 1
  },
  {
    "name": "Artix",
    "count": 1
  },
  {
    "name": "Nobo Kids",
    "count": 1
  },
  {
    "name": "Super Glue",
    "count": 1
  },
  {
    "name": "Total",
    "count": 1
  },
  {
    "name": "Sweet Colours",
    "count": 1
  },
  {
    "name": "inny (Qumak-Sekom)",
    "count": 1
  },
  {
    "name": "Moosee",
    "count": 1
  },
  {
    "name": "Klocki",
    "count": 1
  },
  {
    "name": "Astrino",
    "count": 1
  },
  {
    "name": "PBS",
    "count": 1
  },
  {
    "name": "Jumbo",
    "count": 1
  },
  {
    "name": "3M Peltor",
    "count": 1
  },
  {
    "name": "Dino",
    "count": 1
  },
  {
    "name": "Huanger",
    "count": 1
  },
  {
    "name": "Eurobatt",
    "count": 1
  },
  {
    "name": "Moxy",
    "count": 1
  },
  {
    "name": "Koh i noor",
    "count": 1
  },
  {
    "name": "Paper-mate",
    "count": 1
  },
  {
    "name": "Inna",
    "count": 1
  },
  {
    "name": "WYDAWNICTWO \"MD\" MONIKA DUDA",
    "count": 1
  },
  {
    "name": "Linex",
    "count": 1
  },
  {
    "name": "AB",
    "count": 1
  },
  {
    "name": "Kontext",
    "count": 1
  },
  {
    "name": "Diabolo",
    "count": 1
  },
  {
    "name": "Puma",
    "count": 1
  },
  {
    "name": "QULKI",
    "count": 1
  },
  {
    "name": "Tomdorix",
    "count": 1
  },
  {
    "name": "Addo",
    "count": 1
  },
  {
    "name": "Coil",
    "count": 1
  },
  {
    "name": "Taurus",
    "count": 1
  },
  {
    "name": "SquishySquishies",
    "count": 1
  },
  {
    "name": "Little Tikes",
    "count": 1
  },
  {
    "name": "Kreska",
    "count": 1
  },
  {
    "name": "Trefl PAP",
    "count": 1
  },
  {
    "name": "KUKURYKU Julia Pogorzelska",
    "count": 1
  },
  {
    "name": "EURO-TRADE SPÓŁKA Z OGRANICZONĄ ODPOWIEDZIALNOŚCIĄ",
    "count": 1
  },
  {
    "name": "Bestawy",
    "count": 1
  },
  {
    "name": "Luksja",
    "count": 1
  },
  {
    "name": "OP",
    "count": 1
  },
  {
    "name": "Anma",
    "count": 1
  },
  {
    "name": "Sorento",
    "count": 1
  },
  {
    "name": "IKS",
    "count": 1
  },
  {
    "name": "Fister",
    "count": 1
  },
  {
    "name": "Speelgoedland",
    "count": 1
  },
  {
    "name": "Madrid Papel",
    "count": 1
  },
  {
    "name": "adidas",
    "count": 1
  },
  {
    "name": "BIG",
    "count": 1
  },
  {
    "name": "Stella Pack SA",
    "count": 1
  },
  {
    "name": "Triplex",
    "count": 1
  },
  {
    "name": "3Z ZIELIŃSKI ŻELEWSKI SPÓŁKA KOMANDYTOWA",
    "count": 1
  },
  {
    "name": "ODDK.  VISUAL SYSTEM. JERZY MARCINEK",
    "count": 1
  },
  {
    "name": "Snoby",
    "count": 1
  },
  {
    "name": "Edding",
    "count": 1
  },
  {
    "name": "Rosa",
    "count": 1
  },
  {
    "name": "CLEMENTONI POLSKA SP. Z O.O.",
    "count": 1
  },
  {
    "name": "Sarantis",
    "count": 1
  },
  {
    "name": "Velvet",
    "count": 1
  },
  {
    "name": "Sun",
    "count": 1
  },
  {
    "name": "Dalpo",
    "count": 1
  }
]